{
  "id": "19bb2cf0-e450-4a5f-ae0d-cbc5e0e0f88b",
  "prevId": "e1ce0757-21f2-45c8-8948-2d8c32a9da18",
  "version": "7",
  "dialect": "postgresql",
  "tables": {
    "public.accounts": {
      "name": "accounts",
      "schema": "",
      "columns": {
        "id": {
          "name": "id",
          "type": "uuid",
          "primaryKey": true,
          "notNull": true,
          "default": "gen_random_uuid()"
        },
        "portfolio_id": {
          "name": "portfolio_id",
          "type": "uuid",
          "primaryKey": false,
          "notNull": true
        },
        "name": {
          "name": "name",
          "type": "text",
          "primaryKey": false,
          "notNull": true
        },
        "description": {
          "name": "description",
          "type": "text",
          "primaryKey": false,
          "notNull": false
        },
        "created_at": {
          "name": "created_at",
          "type": "timestamp with time zone",
          "primaryKey": false,
          "notNull": true,
          "default": "now()"
        },
        "updated_at": {
          "name": "updated_at",
          "type": "timestamp with time zone",
          "primaryKey": false,
          "notNull": true,
          "default": "now()"
        }
      },
      "indexes": {
        "accounts_portfolio_id_idx": {
          "name": "accounts_portfolio_id_idx",
          "columns": [
            {
              "expression": "portfolio_id",
              "isExpression": false,
              "asc": true,
              "nulls": "last"
            }
          ],
          "isUnique": false,
          "concurrently": false,
          "method": "btree",
          "with": {}
        }
      },
      "foreignKeys": {
        "accounts_portfolio_id_portfolios_id_fk": {
          "name": "accounts_portfolio_id_portfolios_id_fk",
          "tableFrom": "accounts",
          "tableTo": "portfolios",
          "columnsFrom": [
            "portfolio_id"
          ],
          "columnsTo": [
            "id"
          ],
          "onDelete": "cascade",
          "onUpdate": "no action"
        }
      },
      "compositePrimaryKeys": {},
      "uniqueConstraints": {},
      "policies": {},
      "checkConstraints": {},
      "isRLSEnabled": false
    },
    "public.dividend_cache": {
      "name": "dividend_cache",
      "schema": "",
      "columns": {
        "ticker": {
          "name": "ticker",
          "type": "text",
          "primaryKey": true,
          "notNull": true
        },
        "payload": {
          "name": "payload",
          "type": "jsonb",
          "primaryKey": false,
          "notNull": true
        },
        "fetched_at": {
          "name": "fetched_at",
          "type": "timestamp with time zone",
          "primaryKey": false,
          "notNull": true,
          "default": "now()"
        }
      },
      "indexes": {},
      "foreignKeys": {},
      "compositePrimaryKeys": {},
      "uniqueConstraints": {},
      "policies": {},
      "checkConstraints": {},
      "isRLSEnabled": false
    },
    "public.dividends": {
      "name": "dividends",
      "schema": "",
      "columns": {
        "id": {
          "name": "id",
          "type": "uuid",
          "primaryKey": true,
          "notNull": true,
          "default": "gen_random_uuid()"
        },
        "holding_id": {
          "name": "holding_id",
          "type": "uuid",
          "primaryKey": false,
          "notNull": true
        },
        "ticker": {
          "name": "ticker",
          "type": "text",
          "primaryKey": false,
          "notNull": true
        },
        "amount_per_share": {
          "name": "amount_per_share",
          "type": "numeric(18, 6)",
          "primaryKey": false,
          "notNull": true
        },
        "total_amount": {
          "name": "total_amount",
          "type": "numeric(18, 6)",
          "primaryKey": false,
          "notNull": true
        },
        "ex_date": {
          "name": "ex_date",
          "type": "date",
          "primaryKey": false,
          "notNull": true
        },
        "pay_date": {
          "name": "pay_date",
          "type": "date",
          "primaryKey": false,
          "notNull": true
        },
        "record_date": {
          "name": "record_date",
          "type": "date",
          "primaryKey": false,
          "notNull": false
        },
        "status": {
          "name": "status",
          "type": "dividend_status",
          "typeSchema": "public",
          "primaryKey": false,
          "notNull": true,
          "default": "'scheduled'"
        },
        "created_at": {
          "name": "created_at",
          "type": "timestamp with time zone",
          "primaryKey": false,
          "notNull": true,
          "default": "now()"
        },
        "updated_at": {
          "name": "updated_at",
          "type": "timestamp with time zone",
          "primaryKey": false,
          "notNull": true,
          "default": "now()"
        }
      },
      "indexes": {
        "dividends_holding_id_idx": {
          "name": "dividends_holding_id_idx",
          "columns": [
            {
              "expression": "holding_id",
              "isExpression": false,
              "asc": true,
              "nulls": "last"
            }
          ],
          "isUnique": false,
          "concurrently": false,
          "method": "btree",
          "with": {}
        },
        "dividends_pay_date_idx": {
          "name": "dividends_pay_date_idx",
          "columns": [
            {
              "expression": "pay_date",
              "isExpression": false,
              "asc": true,
              "nulls": "last"
            }
          ],
          "isUnique": false,
          "concurrently": false,
          "method": "btree",
          "with": {}
        }
      },
      "foreignKeys": {
        "dividends_holding_id_holdings_id_fk": {
          "name": "dividends_holding_id_holdings_id_fk",
          "tableFrom": "dividends",
          "tableTo": "holdings",
          "columnsFrom": [
            "holding_id"
          ],
          "columnsTo": [
            "id"
          ],
          "onDelete": "cascade",
          "onUpdate": "no action"
        }
      },
      "compositePrimaryKeys": {},
      "uniqueConstraints": {},
      "policies": {},
      "checkConstraints": {},
      "isRLSEnabled": false
    },
    "public.holdings": {
      "name": "holdings",
      "schema": "",
      "columns": {
        "id": {
          "name": "id",
          "type": "uuid",
          "primaryKey": true,
          "notNull": true,
          "default": "gen_random_uuid()"
        },
        "account_id": {
          "name": "account_id",
          "type": "uuid",
          "primaryKey": false,
          "notNull": true
        },
        "ticker": {
          "name": "ticker",
          "type": "text",
          "primaryKey": false,
          "notNull": true
        },
        "shares": {
          "name": "shares",
          "type": "numeric(18, 6)",
          "primaryKey": false,
          "notNull": true
        },
        "avg_cost_basis": {
          "name": "avg_cost_basis",
          "type": "numeric(18, 6)",
          "primaryKey": false,
          "notNull": true
        },
        "purchase_date": {
          "name": "purchase_date",
          "type": "date",
          "primaryKey": false,
          "notNull": true
        },
        "created_at": {
          "name": "created_at",
          "type": "timestamp with time zone",
          "primaryKey": false,
          "notNull": true,
          "default": "now()"
        },
        "updated_at": {
          "name": "updated_at",
          "type": "timestamp with time zone",
          "primaryKey": false,
          "notNull": true,
          "default": "now()"
        }
      },
      "indexes": {
        "holdings_account_id_idx": {
          "name": "holdings_account_id_idx",
          "columns": [
            {
              "expression": "account_id",
              "isExpression": false,
              "asc": true,
              "nulls": "last"
            }
          ],
          "isUnique": false,
          "concurrently": false,
          "method": "btree",
          "with": {}
        }
      },
      "foreignKeys": {
        "holdings_account_id_accounts_id_fk": {
          "name": "holdings_account_id_accounts_id_fk",
          "tableFrom": "holdings",
          "tableTo": "accounts",
          "columnsFrom": [
            "account_id"
          ],
          "columnsTo": [
            "id"
          ],
          "onDelete": "cascade",
          "onUpdate": "no action"
        }
      },
      "compositePrimaryKeys": {},
      "uniqueConstraints": {},
      "policies": {},
      "checkConstraints": {},
      "isRLSEnabled": false
    },
    "public.portfolio_value_history": {
      "name": "portfolio_value_history",
      "schema": "",
      "columns": {
        "id": {
          "name": "id",
          "type": "uuid",
          "primaryKey": true,
          "notNull": true,
          "default": "gen_random_uuid()"
        },
        "portfolio_id": {
          "name": "portfolio_id",
          "type": "uuid",
          "primaryKey": false,
          "notNull": true
        },
        "date": {
          "name": "date",
          "type": "date",
          "primaryKey": false,
          "notNull": true
        },
        "total_value": {
          "name": "total_value",
          "type": "numeric(18, 6)",
          "primaryKey": false,
          "notNull": true
        },
        "cost_basis": {
          "name": "cost_basis",
          "type": "numeric(18, 6)",
          "primaryKey": false,
          "notNull": true
        },
        "is_partial": {
          "name": "is_partial",
          "type": "boolean",
          "primaryKey": false,
          "notNull": true,
          "default": false
        },
        "created_at": {
          "name": "created_at",
          "type": "timestamp with time zone",
          "primaryKey": false,
          "notNull": true,
          "default": "now()"
        }
      },
      "indexes": {
        "portfolio_value_history_portfolio_date_idx": {
          "name": "portfolio_value_history_portfolio_date_idx",
          "columns": [
            {
              "expression": "portfolio_id",
              "isExpression": false,
              "asc": true,
              "nulls": "last"
            },
            {
              "expression": "date",
              "isExpression": false,
              "asc": true,
              "nulls": "last"
            }
          ],
          "isUnique": true,
          "concurrently": false,
          "method": "btree",
          "with": {}
        }
      },
      "foreignKeys": {
        "portfolio_value_history_portfolio_id_portfolios_id_fk": {
          "name": "portfolio_value_history_portfolio_id_portfolios_id_fk",
          "tableFrom": "portfolio_value_history",
          "tableTo": "portfolios",
          "columnsFrom": [
            "portfolio_id"
          ],
          "columnsTo": [
            "id"
          ],
          "onDelete": "cascade",
          "onUpdate": "no action"
        }
      },
      "compositePrimaryKeys": {},
      "uniqueConstraints": {},
      "policies": {},
      "checkConstraints": {},
      "isRLSEnabled": false
    },
    "public.portfolios": {
      "name": "portfolios",
      "schema": "",
      "columns": {
        "id": {
          "name": "id",
          "type": "uuid",
          "primaryKey": true,
          "notNull": true,
          "default": "gen_random_uuid()"
        },
        "user_id": {
          "name": "user_id",
          "type": "text",
          "primaryKey": false,
          "notNull": true
        },
        "name": {
          "name": "name",
          "type": "text",
          "primaryKey": false,
          "notNull": true
        },
        "description": {
          "name": "description",
          "type": "text",
          "primaryKey": false,
          "notNull": false
        },
        "created_at": {
          "name": "created_at",
          "type": "timestamp with time zone",
          "primaryKey": false,
          "notNull": true,
          "default": "now()"
        },
        "updated_at": {
          "name": "updated_at",
          "type": "timestamp with time zone",
          "primaryKey": false,
          "notNull": true,
          "default": "now()"
        }
      },
      "indexes": {
        "portfolios_user_id_idx": {
          "name": "portfolios_user_id_idx",
          "columns": [
            {
              "expression": "user_id",
              "isExpression": false,
              "asc": true,
              "nulls": "last"
            }
          ],
          "isUnique": false,
          "concurrently": false,
          "method": "btree",
          "with": {}
        }
      },
      "foreignKeys": {},
      "compositePrimaryKeys": {},
      "uniqueConstraints": {},
      "policies": {},
      "checkConstraints": {},
      "isRLSEnabled": false
    },
    "public.price_history": {
      "name": "price_history",
      "schema": "",
      "columns": {
        "ticker": {
          "name": "ticker",
          "type": "text",
          "primaryKey": false,
          "notNull": true
        },
        "date": {
          "name": "date",
          "type": "date",
          "primaryKey": false,
          "notNull": true
        },
        "close_price": {
          "name": "close_price",
          "type": "numeric(18, 6)",
          "primaryKey": false,
          "notNull": true
        },
        "fetched_at": {
          "name": "fetched_at",
          "type": "timestamp with time zone",
          "primaryKey": false,
          "notNull": true,
          "default": "now()"
        }
      },
      "indexes": {
        "price_history_ticker_idx": {
          "name": "price_history_ticker_idx",
          "columns": [
            {
              "expression": "ticker",
              "isExpression": false,
              "asc": true,
              "nulls": "last"
            }
          ],
          "isUnique": false,
          "concurrently": false,
          "method": "btree",
          "with": {}
        },
        "price_history_date_idx": {
          "name": "price_history_date_idx",
          "columns": [
            {
              "expression": "date",
              "isExpression": false,
              "asc": true,
              "nulls": "last"
            }
          ],
          "isUnique": false,
          "concurrently": false,
          "method": "btree",
          "with": {}
        }
      },
      "foreignKeys": {},
      "compositePrimaryKeys": {
        "price_history_ticker_date_pk": {
          "name": "price_history_ticker_date_pk",
          "columns": [
            "ticker",
            "date"
          ]
        }
      },
      "uniqueConstraints": {},
      "policies": {},
      "checkConstraints": {},
      "isRLSEnabled": false
    },
    "public.account": {
      "name": "account",
      "schema": "",
      "columns": {
        "id": {
          "name": "id",
          "type": "text",
          "primaryKey": true,
          "notNull": true
        },
        "account_id": {
          "name": "account_id",
          "type": "text",
          "primaryKey": false,
          "notNull": true
        },
        "provider_id": {
          "name": "provider_id",
          "type": "text",
          "primaryKey": false,
          "notNull": true
        },
        "user_id": {
          "name": "user_id",
          "type": "text",
          "primaryKey": false,
          "notNull": true
        },
        "access_token": {
          "name": "access_token",
          "type": "text",
          "primaryKey": false,
          "notNull": false
        },
        "refresh_token": {
          "name": "refresh_token",
          "type": "text",
          "primaryKey": false,
          "notNull": false
        },
        "id_token": {
          "name": "id_token",
          "type": "text",
          "primaryKey": false,
          "notNull": false
        },
        "access_token_expires_at": {
          "name": "access_token_expires_at",
          "type": "timestamp",
          "primaryKey": false,
          "notNull": false
        },
        "refresh_token_expires_at": {
          "name": "refresh_token_expires_at",
          "type": "timestamp",
          "primaryKey": false,
          "notNull": false
        },
        "scope": {
          "name": "scope",
          "type": "text",
          "primaryKey": false,
          "notNull": false
        },
        "password": {
          "name": "password",
          "type": "text",
          "primaryKey": false,
          "notNull": false
        },
        "created_at": {
          "name": "created_at",
          "type": "timestamp",
          "primaryKey": false,
          "notNull": true,
          "default": "now()"
        },
        "updated_at": {
          "name": "updated_at",
          "type": "timestamp",
          "primaryKey": false,
          "notNull": true
        }
      },
      "indexes": {
        "account_userId_idx": {
          "name": "account_userId_idx",
          "columns": [
            {
              "expression": "user_id",
              "isExpression": false,
              "asc": true,
              "nulls": "last"
            }
          ],
          "isUnique": false,
          "concurrently": false,
          "method": "btree",
          "with": {}
        }
      },
      "foreignKeys": {
        "account_user_id_user_id_fk": {
          "name": "account_user_id_user_id_fk",
          "tableFrom": "account",
          "tableTo": "user",
          "columnsFrom": [
            "user_id"
          ],
          "columnsTo": [
            "id"
          ],
          "onDelete": "cascade",
          "onUpdate": "no action"
        }
      },
      "compositePrimaryKeys": {},
      "uniqueConstraints": {},
      "policies": {},
      "checkConstraints": {},
      "isRLSEnabled": false
    },
    "public.session": {
      "name": "session",
      "schema": "",
      "columns": {
        "id": {
          "name": "id",
          "type": "text",
          "primaryKey": true,
          "notNull": true
        },
        "expires_at": {
          "name": "expires_at",
          "type": "timestamp",
          "primaryKey": false,
          "notNull": true
        },
        "token": {
          "name": "token",
          "type": "text",
          "primaryKey": false,
          "notNull": true
        },
        "created_at": {
          "name": "created_at",
          "type": "timestamp",
          "primaryKey": false,
          "notNull": true,
          "default": "now()"
        },
        "updated_at": {
          "name": "updated_at",
          "type": "timestamp",
          "primaryKey": false,
          "notNull": true
        },
        "ip_address": {
          "name": "ip_address",
          "type": "text",
          "primaryKey": false,
          "notNull": false
        },
        "user_agent": {
          "name": "user_agent",
          "type": "text",
          "primaryKey": false,
          "notNull": false
        },
        "user_id": {
          "name": "user_id",
          "type": "text",
          "primaryKey": false,
          "notNull": true
        }
      },
      "indexes": {
        "session_userId_idx": {
          "name": "session_userId_idx",
          "columns": [
            {
              "expression": "user_id",
              "isExpression": false,
              "asc": true,
              "nulls": "last"
            }
          ],
          "isUnique": false,
          "concurrently": false,
          "method": "btree",
          "with": {}
        }
      },
      "foreignKeys": {
        "session_user_id_user_id_fk": {
          "name": "session_user_id_user_id_fk",
          "tableFrom": "session",
          "tableTo": "user",
          "columnsFrom": [
            "user_id"
          ],
          "columnsTo": [
            "id"
          ],
          "onDelete": "cascade",
          "onUpdate": "no action"
        }
      },
      "compositePrimaryKeys": {},
      "uniqueConstraints": {
        "session_token_unique": {
          "name": "session_token_unique",
          "nullsNotDistinct": false,
          "columns": [
            "token"
          ]
        }
      },
      "policies": {},
      "checkConstraints": {},
      "isRLSEnabled": false
    },
    "public.user": {
      "name": "user",
      "schema": "",
      "columns": {
        "id": {
          "name": "id",
          "type": "text",
          "primaryKey": true,
          "notNull": true
        },
        "name": {
          "name": "name",
          "type": "text",
          "primaryKey": false,
          "notNull": true
        },
        "email": {
          "name": "email",
          "type": "text",
          "primaryKey": false,
          "notNull": true
        },
        "email_verified": {
          "name": "email_verified",
          "type": "boolean",
          "primaryKey": false,
          "notNull": true,
          "default": false
        },
        "image": {
          "name": "image",
          "type": "text",
          "primaryKey": false,
          "notNull": false
        },
        "theme": {
          "name": "theme",
          "type": "text",
          "primaryKey": false,
          "notNull": true,
          "default": "'light'"
        },
        "created_at": {
          "name": "created_at",
          "type": "timestamp",
          "primaryKey": false,
          "notNull": true,
          "default": "now()"
        },
        "updated_at": {
          "name": "updated_at",
          "type": "timestamp",
          "primaryKey": false,
          "notNull": true,
          "default": "now()"
        }
      },
      "indexes": {},
      "foreignKeys": {},
      "compositePrimaryKeys": {},
      "uniqueConstraints": {
        "user_email_unique": {
          "name": "user_email_unique",
          "nullsNotDistinct": false,
          "columns": [
            "email"
          ]
        }
      },
      "policies": {},
      "checkConstraints": {},
      "isRLSEnabled": false
    },
    "public.verification": {
      "name": "verification",
      "schema": "",
      "columns": {
        "id": {
          "name": "id",
          "type": "text",
          "primaryKey": true,
          "notNull": true
        },
        "identifier": {
          "name": "identifier",
          "type": "text",
          "primaryKey": false,
          "notNull": true
        },
        "value": {
          "name": "value",
          "type": "text",
          "primaryKey": false,
          "notNull": true
        },
        "expires_at": {
          "name": "expires_at",
          "type": "timestamp",
          "primaryKey": false,
          "notNull": true
        },
        "created_at": {
          "name": "created_at",
          "type": "timestamp",
          "primaryKey": false,
          "notNull": true,
          "default": "now()"
        },
        "updated_at": {
          "name": "updated_at",
          "type": "timestamp",
          "primaryKey": false,
          "notNull": true,
          "default": "now()"
        }
      },
      "indexes": {
        "verification_identifier_idx": {
          "name": "verification_identifier_idx",
          "columns": [
            {
              "expression": "identifier",
              "isExpression": false,
              "asc": true,
              "nulls": "last"
            }
          ],
          "isUnique": false,
          "concurrently": false,
          "method": "btree",
          "with": {}
        }
      },
      "foreignKeys": {},
      "compositePrimaryKeys": {},
      "uniqueConstraints": {},
      "policies": {},
      "checkConstraints": {},
      "isRLSEnabled": false
    }
  },
  "enums": {
    "public.dividend_status": {
      "name": "dividend_status",
      "schema": "public",
      "values": [
        "scheduled",
        "projected",
        "paid"
      ]
    }
  },
  "schemas": {},
  "sequences": {},
  "roles": {},
  "policies": {},
  "views": {},
  "_meta": {
    "columns": {},
    "schemas": {},
    "tables": {}
  }
}